cyeld/__init__.py
cyeld/core.py
cyeld/core_simple.py
cyeld/cuda.py
cyeld/dataloaders.py
cyeld/datasets.py
cyeld/functions.py
cyeld/functions_conv.py
cyeld/layers.py
cyeld/models.py
cyeld/optimizers.py
cyeld/transforms.py
cyeld/utils.py
cyeld-0.0.1.dist-info/LICENSE
cyeld-0.0.1.dist-info/METADATA
cyeld-0.0.1.dist-info/WHEEL
cyeld-0.0.1.dist-info/top_level.txt
cyeld-0.0.1.dist-info/RECORD
