Metadata-Version: 2.1
Name: cyeld
Version: 0.0.1
Summary: Deep Learning Framework from Cyeld
Home-page: https://github.com/kaitoohsiro/Cyeld
Author: Kaito Oshiro
Author-email: kaitooshiro7@gmail.com
License: MIT License
Platform: UNKNOWN
License-File: LICENSE
Requires-Dist: numpy
